euclidean_species/__init__.py
euclidean_species/main.py
euclidean_specie-1.0.5.dist-info/METADATA
euclidean_specie-1.0.5.dist-info/WHEEL
euclidean_specie-1.0.5.dist-info/entry_points.txt
euclidean_specie-1.0.5.dist-info/top_level.txt
euclidean_specie-1.0.5.dist-info/RECORD
