Metadata-Version: 2.1
Name: euclidean_specie
Version: 1.0.5
Requires-Python: >=3.6
Requires-Dist: numpy
Requires-Dist: matplotlib
